{"frames": {

"WILD X 3_00000":
{
	"frame": {"x":1463,"y":444,"w":142,"h":145},
	"rotated": false,
	"trimmed": true,
	"spriteSourceSize": {"x":0,"y":10,"w":142,"h":145},
	"sourceSize": {"w":142,"h":439}
},
"WILD X 3_00001":
{
	"frame": {"x":1317,"y":444,"w":142,"h":164},
	"rotated": false,
	"trimmed": true,
	"spriteSourceSize": {"x":0,"y":9,"w":142,"h":164},
	"sourceSize": {"w":142,"h":439}
},
"WILD X 3_00002":
{
	"frame": {"x":587,"y":1767,"w":142,"h":192},
	"rotated": false,
	"trimmed": true,
	"spriteSourceSize": {"x":0,"y":0,"w":142,"h":192},
	"sourceSize": {"w":142,"h":439}
},
"WILD X 3_00003":
{
	"frame": {"x":441,"y":1767,"w":142,"h":211},
	"rotated": false,
	"trimmed": true,
	"spriteSourceSize": {"x":0,"y":0,"w":142,"h":211},
	"sourceSize": {"w":142,"h":439}
},
"WILD X 3_00004":
{
	"frame": {"x":295,"y":1767,"w":142,"h":225},
	"rotated": false,
	"trimmed": true,
	"spriteSourceSize": {"x":0,"y":5,"w":142,"h":225},
	"sourceSize": {"w":142,"h":439}
},
"WILD X 3_00005":
{
	"frame": {"x":149,"y":1767,"w":142,"h":246},
	"rotated": false,
	"trimmed": true,
	"spriteSourceSize": {"x":0,"y":3,"w":142,"h":246},
	"sourceSize": {"w":142,"h":439}
},
"WILD X 3_00006":
{
	"frame": {"x":3,"y":1767,"w":142,"h":266},
	"rotated": false,
	"trimmed": true,
	"spriteSourceSize": {"x":0,"y":2,"w":142,"h":266},
	"sourceSize": {"w":142,"h":439}
},
"WILD X 3_00007":
{
	"frame": {"x":733,"y":1750,"w":142,"h":286},
	"rotated": false,
	"trimmed": true,
	"spriteSourceSize": {"x":0,"y":1,"w":142,"h":286},
	"sourceSize": {"w":142,"h":439}
},
"WILD X 3_00008":
{
	"frame": {"x":1171,"y":444,"w":142,"h":306},
	"rotated": false,
	"trimmed": true,
	"spriteSourceSize": {"x":0,"y":0,"w":142,"h":306},
	"sourceSize": {"w":142,"h":439}
},
"WILD X 3_00009":
{
	"frame": {"x":1025,"y":444,"w":142,"h":325},
	"rotated": false,
	"trimmed": true,
	"spriteSourceSize": {"x":0,"y":0,"w":142,"h":325},
	"sourceSize": {"w":142,"h":439}
},
"WILD X 3_00010":
{
	"frame": {"x":879,"y":1602,"w":142,"h":344},
	"rotated": false,
	"trimmed": true,
	"spriteSourceSize": {"x":0,"y":0,"w":142,"h":344},
	"sourceSize": {"w":142,"h":439}
},
"WILD X 3_00011":
{
	"frame": {"x":879,"y":1235,"w":142,"h":363},
	"rotated": false,
	"trimmed": true,
	"spriteSourceSize": {"x":0,"y":0,"w":142,"h":363},
	"sourceSize": {"w":142,"h":439}
},
"WILD X 3_00012":
{
	"frame": {"x":879,"y":849,"w":142,"h":382},
	"rotated": false,
	"trimmed": true,
	"spriteSourceSize": {"x":0,"y":0,"w":142,"h":382},
	"sourceSize": {"w":142,"h":439}
},
"WILD X 3_00013":
{
	"frame": {"x":879,"y":444,"w":142,"h":401},
	"rotated": false,
	"trimmed": true,
	"spriteSourceSize": {"x":0,"y":0,"w":142,"h":401},
	"sourceSize": {"w":142,"h":439}
},
"WILD X 3_00014":
{
	"frame": {"x":733,"y":1326,"w":142,"h":420},
	"rotated": false,
	"trimmed": true,
	"spriteSourceSize": {"x":0,"y":0,"w":142,"h":420},
	"sourceSize": {"w":142,"h":439}
},
"WILD X 3_00015":
{
	"frame": {"x":3,"y":3,"w":142,"h":437},
	"rotated": false,
	"trimmed": true,
	"spriteSourceSize": {"x":0,"y":0,"w":142,"h":437},
	"sourceSize": {"w":142,"h":439}
},
"WILD X 3_00016":
{
	"frame": {"x":3,"y":444,"w":142,"h":437},
	"rotated": false,
	"trimmed": true,
	"spriteSourceSize": {"x":0,"y":0,"w":142,"h":437},
	"sourceSize": {"w":142,"h":439}
},
"WILD X 3_00017":
{
	"frame": {"x":3,"y":885,"w":142,"h":437},
	"rotated": false,
	"trimmed": true,
	"spriteSourceSize": {"x":0,"y":0,"w":142,"h":437},
	"sourceSize": {"w":142,"h":439}
},
"WILD X 3_00018":
{
	"frame": {"x":3,"y":1326,"w":142,"h":437},
	"rotated": false,
	"trimmed": true,
	"spriteSourceSize": {"x":0,"y":0,"w":142,"h":437},
	"sourceSize": {"w":142,"h":439}
},
"WILD X 3_00019":
{
	"frame": {"x":149,"y":3,"w":142,"h":437},
	"rotated": false,
	"trimmed": true,
	"spriteSourceSize": {"x":0,"y":0,"w":142,"h":437},
	"sourceSize": {"w":142,"h":439}
},
"WILD X 3_00020":
{
	"frame": {"x":149,"y":444,"w":142,"h":437},
	"rotated": false,
	"trimmed": true,
	"spriteSourceSize": {"x":0,"y":0,"w":142,"h":437},
	"sourceSize": {"w":142,"h":439}
},
"WILD X 3_00021":
{
	"frame": {"x":149,"y":885,"w":142,"h":437},
	"rotated": false,
	"trimmed": true,
	"spriteSourceSize": {"x":0,"y":0,"w":142,"h":437},
	"sourceSize": {"w":142,"h":439}
},
"WILD X 3_00022":
{
	"frame": {"x":149,"y":1326,"w":142,"h":437},
	"rotated": false,
	"trimmed": true,
	"spriteSourceSize": {"x":0,"y":0,"w":142,"h":437},
	"sourceSize": {"w":142,"h":439}
},
"WILD X 3_00023":
{
	"frame": {"x":295,"y":3,"w":142,"h":437},
	"rotated": false,
	"trimmed": true,
	"spriteSourceSize": {"x":0,"y":0,"w":142,"h":437},
	"sourceSize": {"w":142,"h":439}
},
"WILD X 3_00024":
{
	"frame": {"x":295,"y":444,"w":142,"h":437},
	"rotated": false,
	"trimmed": true,
	"spriteSourceSize": {"x":0,"y":0,"w":142,"h":437},
	"sourceSize": {"w":142,"h":439}
},
"WILD X 3_00025":
{
	"frame": {"x":295,"y":885,"w":142,"h":437},
	"rotated": false,
	"trimmed": true,
	"spriteSourceSize": {"x":0,"y":0,"w":142,"h":437},
	"sourceSize": {"w":142,"h":439}
},
"WILD X 3_00026":
{
	"frame": {"x":295,"y":1326,"w":142,"h":437},
	"rotated": false,
	"trimmed": true,
	"spriteSourceSize": {"x":0,"y":0,"w":142,"h":437},
	"sourceSize": {"w":142,"h":439}
},
"WILD X 3_00027":
{
	"frame": {"x":441,"y":3,"w":142,"h":437},
	"rotated": false,
	"trimmed": true,
	"spriteSourceSize": {"x":0,"y":0,"w":142,"h":437},
	"sourceSize": {"w":142,"h":439}
},
"WILD X 3_00028":
{
	"frame": {"x":441,"y":444,"w":142,"h":437},
	"rotated": false,
	"trimmed": true,
	"spriteSourceSize": {"x":0,"y":0,"w":142,"h":437},
	"sourceSize": {"w":142,"h":439}
},
"WILD X 3_00029":
{
	"frame": {"x":441,"y":885,"w":142,"h":437},
	"rotated": false,
	"trimmed": true,
	"spriteSourceSize": {"x":0,"y":0,"w":142,"h":437},
	"sourceSize": {"w":142,"h":439}
},
"WILD X 3_00030":
{
	"frame": {"x":441,"y":1326,"w":142,"h":437},
	"rotated": false,
	"trimmed": true,
	"spriteSourceSize": {"x":0,"y":0,"w":142,"h":437},
	"sourceSize": {"w":142,"h":439}
},
"WILD X 3_00031":
{
	"frame": {"x":587,"y":3,"w":142,"h":437},
	"rotated": false,
	"trimmed": true,
	"spriteSourceSize": {"x":0,"y":0,"w":142,"h":437},
	"sourceSize": {"w":142,"h":439}
},
"WILD X 3_00032":
{
	"frame": {"x":587,"y":444,"w":142,"h":437},
	"rotated": false,
	"trimmed": true,
	"spriteSourceSize": {"x":0,"y":0,"w":142,"h":437},
	"sourceSize": {"w":142,"h":439}
},
"WILD X 3_00033":
{
	"frame": {"x":587,"y":885,"w":142,"h":437},
	"rotated": false,
	"trimmed": true,
	"spriteSourceSize": {"x":0,"y":0,"w":142,"h":437},
	"sourceSize": {"w":142,"h":439}
},
"WILD X 3_00034":
{
	"frame": {"x":587,"y":1326,"w":142,"h":437},
	"rotated": false,
	"trimmed": true,
	"spriteSourceSize": {"x":0,"y":0,"w":142,"h":437},
	"sourceSize": {"w":142,"h":439}
},
"WILD X 3_00035":
{
	"frame": {"x":733,"y":3,"w":142,"h":437},
	"rotated": false,
	"trimmed": true,
	"spriteSourceSize": {"x":0,"y":0,"w":142,"h":437},
	"sourceSize": {"w":142,"h":439}
},
"WILD X 3_00036":
{
	"frame": {"x":879,"y":3,"w":142,"h":437},
	"rotated": false,
	"trimmed": true,
	"spriteSourceSize": {"x":0,"y":0,"w":142,"h":437},
	"sourceSize": {"w":142,"h":439}
},
"WILD X 3_00037":
{
	"frame": {"x":1025,"y":3,"w":142,"h":437},
	"rotated": false,
	"trimmed": true,
	"spriteSourceSize": {"x":0,"y":0,"w":142,"h":437},
	"sourceSize": {"w":142,"h":439}
},
"WILD X 3_00038":
{
	"frame": {"x":1171,"y":3,"w":142,"h":437},
	"rotated": false,
	"trimmed": true,
	"spriteSourceSize": {"x":0,"y":0,"w":142,"h":437},
	"sourceSize": {"w":142,"h":439}
},
"WILD X 3_00039":
{
	"frame": {"x":1317,"y":3,"w":142,"h":437},
	"rotated": false,
	"trimmed": true,
	"spriteSourceSize": {"x":0,"y":0,"w":142,"h":437},
	"sourceSize": {"w":142,"h":439}
},
"WILD X 3_00040":
{
	"frame": {"x":1463,"y":3,"w":142,"h":437},
	"rotated": false,
	"trimmed": true,
	"spriteSourceSize": {"x":0,"y":0,"w":142,"h":437},
	"sourceSize": {"w":142,"h":439}
},
"WILD X 3_00041":
{
	"frame": {"x":1609,"y":3,"w":142,"h":437},
	"rotated": false,
	"trimmed": true,
	"spriteSourceSize": {"x":0,"y":0,"w":142,"h":437},
	"sourceSize": {"w":142,"h":439}
},
"WILD X 3_00042":
{
	"frame": {"x":1755,"y":3,"w":142,"h":437},
	"rotated": false,
	"trimmed": true,
	"spriteSourceSize": {"x":0,"y":0,"w":142,"h":437},
	"sourceSize": {"w":142,"h":439}
},
"WILD X 3_00043":
{
	"frame": {"x":1901,"y":3,"w":142,"h":437},
	"rotated": false,
	"trimmed": true,
	"spriteSourceSize": {"x":0,"y":0,"w":142,"h":437},
	"sourceSize": {"w":142,"h":439}
},
"WILD X 3_00044":
{
	"frame": {"x":733,"y":444,"w":142,"h":437},
	"rotated": false,
	"trimmed": true,
	"spriteSourceSize": {"x":0,"y":0,"w":142,"h":437},
	"sourceSize": {"w":142,"h":439}
},
"WILD X 3_00045":
{
	"frame": {"x":733,"y":885,"w":142,"h":437},
	"rotated": false,
	"trimmed": true,
	"spriteSourceSize": {"x":0,"y":0,"w":142,"h":437},
	"sourceSize": {"w":142,"h":439}
}},
"animations": {
	"WILD X 3": ["WILD X 3_00000","WILD X 3_00001","WILD X 3_00002","WILD X 3_00003","WILD X 3_00004","WILD X 3_00005","WILD X 3_00006","WILD X 3_00007","WILD X 3_00008","WILD X 3_00009","WILD X 3_00010","WILD X 3_00011","WILD X 3_00012","WILD X 3_00013","WILD X 3_00014","WILD X 3_00015","WILD X 3_00016","WILD X 3_00017","WILD X 3_00018","WILD X 3_00019","WILD X 3_00020","WILD X 3_00021","WILD X 3_00022","WILD X 3_00023","WILD X 3_00024","WILD X 3_00025","WILD X 3_00026","WILD X 3_00027","WILD X 3_00028","WILD X 3_00029","WILD X 3_00030","WILD X 3_00031","WILD X 3_00032","WILD X 3_00033","WILD X 3_00034","WILD X 3_00035","WILD X 3_00036","WILD X 3_00037","WILD X 3_00038","WILD X 3_00039","WILD X 3_00040","WILD X 3_00041","WILD X 3_00042","WILD X 3_00043","WILD X 3_00044","WILD X 3_00045"]
},
"meta": {
	"app": "https://www.codeandweb.com/texturepacker",
	"version": "1.0",
	"image": "symbolAnimation_0_expanding.png",
	"format": "RGBA8888",
	"size": {"w":2048,"h":2048},
	"scale": "0.4",
	"smartupdate": "$TexturePacker:SmartUpdate:24213b567fa637c47f2369b09d5e33c4:8af82ff0954c62a2de19a142f5864872:42e16a2152b42be8a45a5ff90e3cf95f$"
}
}
